autocrop/__init__.py
autocrop/main.py
autocrop_video-0.1.1.dist-info/METADATA
autocrop_video-0.1.1.dist-info/WHEEL
autocrop_video-0.1.1.dist-info/entry_points.txt
autocrop_video-0.1.1.dist-info/licenses/LICENCE
autocrop_video-0.1.1.dist-info/RECORD
